brandedpipes.py
brandedpipes-0.0.1.dist-info/METADATA
brandedpipes-0.0.1.dist-info/WHEEL
brandedpipes-0.0.1.dist-info/top_level.txt
brandedpipes-0.0.1.dist-info/RECORD
